main.py
bachai_data_analysis_mcp-1.1.6.dist-info/METADATA
bachai_data_analysis_mcp-1.1.6.dist-info/WHEEL
bachai_data_analysis_mcp-1.1.6.dist-info/entry_points.txt
bachai_data_analysis_mcp-1.1.6.dist-info/top_level.txt
bachai_data_analysis_mcp-1.1.6.dist-info/RECORD
