Metadata-Version: 2.4
Name: bachai-data-analysis-mcp
Version: 1.1.6
Summary: Data Analysis MCP Server - Model Context Protocol server for data analysis (stdio and SSE modes)
Home-page: https://github.com/BACH-AI-Tools/data-analysis-mcp
Author: BACH Studio
Author-email: BACH Studio <contact@bachstudio.com>
License: MIT
Project-URL: Homepage, https://github.com/BACH-AI-Tools/data-analysis-mcp
Keywords: mcp,data-analysis,pandas,machine-learning,sse
Classifier: Programming Language :: Python :: 3
Classifier: License :: OSI Approved :: MIT License
Classifier: Operating System :: OS Independent
Requires-Python: >=3.7
Requires-Dist: pandas>=2.0.0
Requires-Dist: numpy>=1.24.0
Requires-Dist: matplotlib>=3.7.0
Requires-Dist: seaborn>=0.12.0
Requires-Dist: openpyxl>=3.1.0
Requires-Dist: fastapi>=0.104.0
Requires-Dist: uvicorn>=0.24.0
Requires-Dist: sse-starlette>=1.8.0
Requires-Dist: httpx>=0.25.0
Dynamic: author
Dynamic: home-page
Dynamic: requires-python
